damn_fastkafka/__init__.py
damn_fastkafka/decorators.py
damn_fastkafka/exceptions.py
damn_fastkafka/kafka.py
damn_fastkafka/kafka_base.py
damn_fastkafka/kafka_service.py
damn_fastkafka/logger.py
damn_fastkafka/schemas.py
damn_fastkafka/serialization.py
damn_fastkafka-0.1.0.dist-info/METADATA
damn_fastkafka-0.1.0.dist-info/WHEEL
damn_fastkafka-0.1.0.dist-info/top_level.txt
damn_fastkafka-0.1.0.dist-info/RECORD
