Metadata-Version: 2.1
Name: damn-fastkafka
Version: 0.1.0
Summary: This is the simplest module for quick work with Kafka.
Home-page: https://gitlab.com/nmModi/damn_fastkafka
Author: mniyazkhanov@gmail.com
Author-email: mniyazkhanov@gmail.com
License: UNKNOWN
Project-URL: Source, https://gitlab.com/nmModi/damn_fastkafka
Keywords: kafka fastapi
Platform: UNKNOWN
Classifier: Programming Language :: Python :: 3.11
Classifier: License :: OSI Approved :: MIT License
Classifier: Operating System :: OS Independent
Requires-Python: >=3.8
Requires-Dist: aiokafka (>=0.7.2)
Requires-Dist: aiologger (>=0.6.0)
Requires-Dist: pydantic (>=1.8)
